<?xml version="1.0" encoding="UTF-8"?>
<File>
  <OriginatingSystemId>Cerfa-1244771-ID10506</OriginatingSystemId>
  <RegisteredDate>2104-10-30T23:00:00</RegisteredDate>
  <Event>
    <EventIdentifier>AUT-234584</EventIdentifier>
    <EventTypeCode>Autorisation</EventTypeCode>
    <EventDateTime>2104-11-13T11:00:00</EventDateTime>
    <OutCome>KO</OutCome>
  </Event>
  <Requirer>
    <Identifier>REF-98B703569D18</Identifier>
    <FirstName>Mélanie</FirstName>
    <BirthName>ROMIN</BirthName>
  </Requirer>
  <Frog>
    <CommonName>Verte à détente</CommonName>
    <ScientificName>Viridi Rana Elasticis</ScientificName>
  </Frog>
  <Frog>
    <CommonName>Rouge à laser</CommonName>
    <ScientificName>Rubra Rana Laseri</ScientificName>
  </Frog>
</File>
